{
	"usage": "vectorLerp(<from>, <to>, <fraction>)",
	"description": [
		"Linear interpolates between two vectors."
	],
	"params": [
		{
			"name": "from",
			"types": ["Vector3"],
			"description": [
				"The vector whose value is used when fraction is 0."
			]
		},
		{
			"name": "to",
			"types": ["Vector3"],
			"description": [
				"The vector whose value is used when fraction is 1."
			]
		},
		{
			"name": "fraction",
			"types": ["float"],
			"description": [
				"The fraction of the way between vectors. Values less than 0 or greater than 1 do linear extrapolation."
			]
		}
	],
	"return": {
		"types": ["Vector3"]
	},
	"example": [
		"color = vectorLerp(oldColor, newColor, timeElapsed / timeTotal);"
	]
}
