{
	"usage": "<entity> setLightFovRange(<fov outer>, <fov inner>)",
	"description": [
		"Sets the current radius of the light."
	],
	"params": [
		{
			"name": "fov outer",
			"types": ["int"],
			"description": [
				"A new value for the outer FOV of the light, in degrees. This cannot be larger than the FOV when the map was compiled, or less than 1."
			],
			"optional": false
		},
		{
			"name": "fov inner",
			"types": ["int"],
			"description": [
				"A new value for the inner FOV of the light, in degrees. This cannot be larger than fov outer, or less than 0. If not specified, the map value is used."
			],
			"optional": true
		}
	],
	"example": [
		"self setLightFovRange(outer, inner);"
	]
}
